temdb/client/__init__.py
temdb/client/_client.py
temdb/client/exceptions.py
temdb/client/resources/__init__.py
temdb/client/resources/acquisition.py
temdb/client/resources/base.py
temdb/client/resources/block.py
temdb/client/resources/cutting_session.py
temdb/client/resources/roi.py
temdb/client/resources/section.py
temdb/client/resources/specimen.py
temdb/client/resources/substrate.py
temdb/client/resources/task.py
temdb/client/resources/sync_wrappers/__init__.py
temdb/client/resources/sync_wrappers/acquisition.py
temdb/client/resources/sync_wrappers/block.py
temdb/client/resources/sync_wrappers/cutting_session.py
temdb/client/resources/sync_wrappers/roi.py
temdb/client/resources/sync_wrappers/section.py
temdb/client/resources/sync_wrappers/specimen.py
temdb/client/resources/sync_wrappers/substrate.py
temdb/client/resources/sync_wrappers/task.py
temdb_client-2.0.0.dist-info/METADATA
temdb_client-2.0.0.dist-info/WHEEL
temdb_client-2.0.0.dist-info/RECORD
