Metadata-Version: 2.4
Name: temdb-client
Version: 2.0.0
Summary: Python client SDK for TEMdb API
Requires-Python: >=3.10
Requires-Dist: httpx>=0.25
Requires-Dist: pydantic>=2.0
Requires-Dist: temdb-models>=2.0.0
Requires-Dist: tenacity>=8.0
